chatterbot_weather/__init__.py
chatterbot_weather/weather_adapter.py
chatterbot_weather-0.1.1.dist-info/DESCRIPTION.rst
chatterbot_weather-0.1.1.dist-info/METADATA
chatterbot_weather-0.1.1.dist-info/RECORD
chatterbot_weather-0.1.1.dist-info/WHEEL
chatterbot_weather-0.1.1.dist-info/metadata.json
chatterbot_weather-0.1.1.dist-info/top_level.txt
chatterbot_weather-0.1.1.dist-info/zip-safe
