Metadata-Version: 2.0
Name: chatterbot-weather
Version: 0.1.1
Summary: 
Requires-Dist: chatterbot (>=0.3.6)
Requires-Dist: python-forecastio (==1.3.4)
